mictools/__init__.py
mictools/mtest.py
mictools/null.py
mictools/pval.py
mictools/strength.py
mictools/utils.py
scripts/__init__.py
scripts/mictools_cmd.py
mictools-1.1.4.dist-info/LICENSE
mictools-1.1.4.dist-info/METADATA
mictools-1.1.4.dist-info/WHEEL
mictools-1.1.4.dist-info/entry_points.txt
mictools-1.1.4.dist-info/top_level.txt
mictools-1.1.4.dist-info/RECORD
