Metadata-Version: 2.1
Name: mictools
Version: 1.1.4
Summary: MICtools
Home-page: https://github.com/minepy/mictools
Author: Davide Albanese
Author-email: davide.albanese@gmail.com
Maintainer: Davide Albanese
Maintainer-email: davide.albanese@gmail.com
License: GPLv3
Download-URL: https://github.com/minepy/mictools/releases
Platform: UNKNOWN
Requires-Dist: Click (>=5.1)
Requires-Dist: matplotlib (>=1.2.0)
Requires-Dist: minepy (>=1.2)
Requires-Dist: numpy (>=1.7.0)
Requires-Dist: pandas (>=0.17.0)
Requires-Dist: scipy (>=0.13)
Requires-Dist: statsmodels (>=0.6.1)
